docker_explorer/__init__.py
docker_explorer/container.py
docker_explorer/downloader.py
docker_explorer/errors.py
docker_explorer/explorer.py
docker_explorer/storage.py
docker_explorer/utils.py
docker_explorer-20191104.data/scripts/de.py
docker_explorer-20191104.dist-info/LICENSE
docker_explorer-20191104.dist-info/METADATA
docker_explorer-20191104.dist-info/WHEEL
docker_explorer-20191104.dist-info/top_level.txt
docker_explorer-20191104.dist-info/RECORD
